{
    "id": 2560,
    "title": "Building Event-Driven Microservices",
    "img": "https://imagebsj.netlify.app/2560.jpeg",
    "author": "Adam Bellemare",
    "language": "英文",
    "publishYear": 2020,
    "programLanguage": "",
    "formats": [
        {
            "fmt": "PDF",
            "title": "城通网盘",
            "link": "/e_books/2560/webstorage_links/8918/to_link"
        },
        {
            "fmt": "EPUB",
            "title": "城通网盘",
            "link": "/e_books/2560/webstorage_links/8919/to_link"
        }
    ]
}