{
    "id": 2568,
    "title": "Full Stack Serverless",
    "img": "https://imagebsj.netlify.app/2568.jpeg",
    "author": "Nader Dabit",
    "language": "英文",
    "publishYear": 2020,
    "programLanguage": "",
    "formats": [
        {
            "fmt": "PDF",
            "title": "城通网盘",
            "link": "/e_books/2568/webstorage_links/8947/to_link"
        },
        {
            "fmt": "EPUB",
            "title": "城通网盘",
            "link": "/e_books/2568/webstorage_links/8948/to_link"
        }
    ]
}