{
    "id": 2938,
    "title": "Spring Boot in Practice",
    "img": "https://imagebsj.netlify.app/2938.jpeg",
    "author": "Somnath Musib",
    "language": "英文",
    "publishYear": 2022,
    "programLanguage": "Java",
    "formats": [
        {
            "fmt": "PDF",
            "title": "城通网盘",
            "link": "/e_books/2938/webstorage_links/10819/to_link"
        },
        {
            "fmt": "EPUB",
            "title": "城通网盘",
            "link": "/e_books/2938/webstorage_links/10818/to_link"
        },
        {
            "fmt": "MOBI",
            "title": "城通网盘",
            "link": "/e_books/2938/webstorage_links/10817/to_link"
        }
    ]
}