{
    "id": 3340,
    "title": "Operating OpenShift",
    "img": "http://image.banshujiang.cn/3340.jpeg?timestamp=1676695359956",
    "author": "Rick Rackow and Manuel Dewald",
    "language": "英文",
    "publishYear": 2022,
    "programLanguage": "",
    "formats": [
        {
            "fmt": "EPUB",
            "title": "城通网盘",
            "link": "/e_books/3340/webstorage_links/17535/to_link"
        },
        {
            "fmt": "MOBI",
            "title": "城通网盘",
            "link": "/e_books/3340/webstorage_links/17534/to_link"
        }
    ]
}