{
    "id": 3352,
    "title": "The Staff Engineer’s Path",
    "img": "http://image.banshujiang.cn/3352.jpeg?timestamp=1676704277806",
    "author": "Tanya Reilly",
    "language": "英文",
    "publishYear": 2022,
    "programLanguage": "",
    "formats": [
        {
            "fmt": "PDF",
            "title": "城通网盘",
            "link": "/e_books/3352/webstorage_links/17569/to_link"
        },
        {
            "fmt": "EPUB",
            "title": "城通网盘",
            "link": "/e_books/3352/webstorage_links/17568/to_link"
        }
    ]
}