[
    {
        "id": 455,
        "title": "Building Android Apps with HTML, CSS, and JavaScript 2nd Edition",
        "img": "https://imagebsj.netlify.app/455.jpeg",
        "author": "Jonathan Stark with Brian Jepson",
        "language": "英文",
        "publishYear": 2012,
        "programLanguage": "HTML5",
        "formats": [
            {
                "fmt": "PDF",
                "title": "城通网盘",
                "link": "/e_books/455/webstorage_links/14426/to_link"
            }
        ]
    },
    {
        "id": 3528,
        "title": "Jetpack Compose by Tutorials 2nd Edition",
        "img": "http://image.banshujiang.cn/3528.jpeg?timestamp=1696771044784",
        "author": "Denis Buketa &amp; Prateek Prasad",
        "language": "英文",
        "publishYear": 2023,
        "programLanguage": "Kotlin",
        "formats": [
            {
                "fmt": "PDF",
                "title": "城通网盘",
                "link": "/e_books/3528/webstorage_links/18365/to_link"
            },
            {
                "fmt": "EPUB",
                "title": "城通网盘",
                "link": "/e_books/3528/webstorage_links/18364/to_link"
            }
        ]
    },
    {
        "id": 3522,
        "title": "Android Accessibility by Tutorials",
        "img": "http://image.banshujiang.cn/3522.jpeg?timestamp=1696770172774",
        "author": "Victoria Gonda",
        "language": "英文",
        "publishYear": 2022,
        "programLanguage": "",
        "formats": [
            {
                "fmt": "PDF",
                "title": "城通网盘",
                "link": "/e_books/3522/webstorage_links/18347/to_link"
            },
            {
                "fmt": "EPUB",
                "title": "城通网盘",
                "link": "/e_books/3522/webstorage_links/18346/to_link"
            }
        ]
    },
    {
        "id": 3463,
        "title": "Responsive Web Design with HTML5 and CSS3 2nd Edition",
        "img": "http://image.banshujiang.cn/3463.jpeg?timestamp=1696338349197",
        "author": "Ben Frain",
        "language": "英文",
        "publishYear": 2015,
        "programLanguage": "HTML5",
        "formats": [
            {
                "fmt": "PDF",
                "title": "城通网盘",
                "link": "/e_books/3463/webstorage_links/18089/to_link"
            },
            {
                "fmt": "EPUB",
                "title": "城通网盘",
                "link": "/e_books/3463/webstorage_links/18088/to_link"
            },
            {
                "fmt": "MOBI",
                "title": "城通网盘",
                "link": "/e_books/3463/webstorage_links/18091/to_link"
            },
            {
                "fmt": "CODE",
                "title": "城通网盘",
                "link": "/e_books/3463/webstorage_links/18090/to_link"
            }
        ]
    },
    {
        "id": 3388,
        "title": "Gradle Recipes for Android",
        "img": "http://image.banshujiang.cn/3388.jpeg?timestamp=1677313529596",
        "author": "Ken Kousen",
        "language": "英文",
        "publishYear": 2016,
        "programLanguage": "Kotlin",
        "formats": [
            {
                "fmt": "PDF",
                "title": "城通网盘",
                "link": "/e_books/3388/webstorage_links/17735/to_link"
            },
            {
                "fmt": "EPUB",
                "title": "城通网盘",
                "link": "/e_books/3388/webstorage_links/17734/to_link"
            }
        ]
    },
    {
        "id": 3296,
        "title": "Reactive Programming with Kotlin",
        "img": "http://image.banshujiang.cn/3296.jpeg?timestamp=1676087594377",
        "author": "Alex Sullivan",
        "language": "英文",
        "publishYear": 2019,
        "programLanguage": "Kotlin",
        "formats": [
            {
                "fmt": "PDF",
                "title": "城通网盘",
                "link": "/e_books/3296/webstorage_links/17389/to_link"
            },
            {
                "fmt": "EPUB",
                "title": "城通网盘",
                "link": "/e_books/3296/webstorage_links/17387/to_link"
            },
            {
                "fmt": "CODE",
                "title": "城通网盘",
                "link": "/e_books/3296/webstorage_links/17388/to_link"
            }
        ]
    },
    {
        "id": 3187,
        "title": "Head First Android Development 2nd Edition",
        "img": "http://image.banshujiang.cn/3187.jpeg?timestamp=1672468865468",
        "author": "Dawn Griffiths",
        "language": "英文",
        "publishYear": 2017,
        "programLanguage": "Java",
        "formats": [
            {
                "fmt": "PDF",
                "title": "城通网盘",
                "link": "/e_books/3187/webstorage_links/16869/to_link"
            },
            {
                "fmt": "EPUB",
                "title": "城通网盘",
                "link": "/e_books/3187/webstorage_links/16870/to_link"
            },
            {
                "fmt": "AZW3",
                "title": "城通网盘",
                "link": "/e_books/3187/webstorage_links/16868/to_link"
            }
        ]
    },
    {
        "id": 3131,
        "title": "Advanced Android App Architecture",
        "img": "https://imagebsj.netlify.app/3131.jpeg",
        "author": "Yun Cheng and Aldo Olivares Domínguez",
        "language": "英文",
        "publishYear": 2019,
        "programLanguage": "Kotlin",
        "formats": [
            {
                "fmt": "PDF",
                "title": "城通网盘",
                "link": "/e_books/3131/webstorage_links/16597/to_link"
            },
            {
                "fmt": "EPUB",
                "title": "城通网盘",
                "link": "/e_books/3131/webstorage_links/16596/to_link"
            },
            {
                "fmt": "CODE",
                "title": "城通网盘",
                "link": "/e_books/3131/webstorage_links/16598/to_link"
            }
        ]
    },
    {
        "id": 3129,
        "title": "Kotlin Coroutines by Tutorials 2nd Edition",
        "img": "https://imagebsj.netlify.app/3129.jpeg",
        "author": "Filip Babić and Nishant Srivastava",
        "language": "英文",
        "publishYear": 2019,
        "programLanguage": "Kotlin",
        "formats": [
            {
                "fmt": "PDF",
                "title": "城通网盘",
                "link": "/e_books/3129/webstorage_links/16590/to_link"
            },
            {
                "fmt": "EPUB",
                "title": "城通网盘",
                "link": "/e_books/3129/webstorage_links/16589/to_link"
            },
            {
                "fmt": "CODE",
                "title": "城通网盘",
                "link": "/e_books/3129/webstorage_links/16588/to_link"
            }
        ]
    },
    {
        "id": 3126,
        "title": "Data Structures &amp; Algorithms in Kotlin",
        "img": "https://imagebsj.netlify.app/3126.jpeg",
        "author": "Irina Galata &amp; Matei Suica",
        "language": "英文",
        "publishYear": 2019,
        "programLanguage": "Kotlin",
        "formats": [
            {
                "fmt": "PDF",
                "title": "城通网盘",
                "link": "/e_books/3126/webstorage_links/16577/to_link"
            },
            {
                "fmt": "EPUB",
                "title": "城通网盘",
                "link": "/e_books/3126/webstorage_links/16576/to_link"
            },
            {
                "fmt": "CODE",
                "title": "城通网盘",
                "link": "/e_books/3126/webstorage_links/16578/to_link"
            }
        ]
    },
    {
        "id": 3122,
        "title": "Android Test-Driven Development by Tutorials",
        "img": "https://imagebsj.netlify.app/3122.jpeg",
        "author": "Lance Gleason, Victoria Gonda and Fernando Sproviero",
        "language": "英文",
        "publishYear": 2019,
        "programLanguage": "Kotlin",
        "formats": [
            {
                "fmt": "PDF",
                "title": "城通网盘",
                "link": "/e_books/3122/webstorage_links/16556/to_link"
            },
            {
                "fmt": "EPUB",
                "title": "城通网盘",
                "link": "/e_books/3122/webstorage_links/16555/to_link"
            },
            {
                "fmt": "CODE",
                "title": "城通网盘",
                "link": "/e_books/3122/webstorage_links/16554/to_link"
            }
        ]
    },
    {
        "id": 3064,
        "title": "Real-World Android by Tutorials 2nd Edition",
        "img": "https://imagebsj.netlify.app/3064.jpeg",
        "author": "Ricardo Costeira, Subhrajyoti Sen, Kolin Stürt &amp; Antonio Roa-Valverde",
        "language": "英文",
        "publishYear": 2022,
        "programLanguage": "Kotlin",
        "formats": [
            {
                "fmt": "PDF",
                "title": "城通网盘",
                "link": "/e_books/3064/webstorage_links/16278/to_link"
            },
            {
                "fmt": "EPUB",
                "title": "城通网盘",
                "link": "/e_books/3064/webstorage_links/16277/to_link"
            }
        ]
    },
    {
        "id": 3061,
        "title": "Responsive Web Design with HTML5 and CSS 4th Edition",
        "img": "https://imagebsj.netlify.app/3061.jpeg",
        "author": "Ben Frain",
        "language": "英文",
        "publishYear": 2022,
        "programLanguage": "HTML5",
        "formats": [
            {
                "fmt": "PDF",
                "title": "城通网盘",
                "link": "/e_books/3061/webstorage_links/16269/to_link"
            },
            {
                "fmt": "EPUB",
                "title": "城通网盘",
                "link": "/e_books/3061/webstorage_links/16270/to_link"
            }
        ]
    },
    {
        "id": 3059,
        "title": "Responsive Web Design with HTML5 and CSS 3rd Edition",
        "img": "https://imagebsj.netlify.app/3059.jpeg",
        "author": "Ben Frain",
        "language": "英文",
        "publishYear": 2020,
        "programLanguage": "HTML5",
        "formats": [
            {
                "fmt": "PDF",
                "title": "城通网盘",
                "link": "/e_books/3059/webstorage_links/16256/to_link"
            },
            {
                "fmt": "EPUB",
                "title": "城通网盘",
                "link": "/e_books/3059/webstorage_links/16257/to_link"
            },
            {
                "fmt": "MOBI",
                "title": "城通网盘",
                "link": "/e_books/3059/webstorage_links/16258/to_link"
            }
        ]
    },
    {
        "id": 3007,
        "title": "Android Programming 4th Edition",
        "img": "https://imagebsj.netlify.app/3007.jpeg",
        "author": "Kristin Marsicano, Brian Gardner, Bill Phillips and Chris Stewart",
        "language": "英文",
        "publishYear": 2019,
        "programLanguage": "Kotlin",
        "formats": [
            {
                "fmt": "PDF",
                "title": "城通网盘",
                "link": "/e_books/3007/webstorage_links/16067/to_link"
            }
        ]
    },
    {
        "id": 2917,
        "title": "Kotlin Multiplatform by Tutorials",
        "img": "https://imagebsj.netlify.app/2917.jpeg",
        "author": "Kevin D. Moore",
        "language": "英文",
        "publishYear": 2022,
        "programLanguage": "Kotlin",
        "formats": [
            {
                "fmt": "PDF",
                "title": "城通网盘",
                "link": "/e_books/2917/webstorage_links/10703/to_link"
            }
        ]
    }
]