[
    {
        "id": 809,
        "title": "Pro iOS Web Design and Development: HTML5, CSS3, and JavaScript with Safari",
        "img": "https://imagebsj.netlify.app/809.jpeg",
        "author": "Andrea Picchi",
        "language": "英文",
        "publishYear": 2011,
        "programLanguage": "HTML5",
        "formats": [
            {
                "fmt": "PDF",
                "title": "城通网盘",
                "link": "/e_books/809/webstorage_links/15132/to_link"
            }
        ]
    },
    {
        "id": 3908,
        "title": "iOS 17 App Development Essentials",
        "img": "http://image.banshujiang.cn/3908.jpeg?timestamp=1714570396489",
        "author": "Neil Smyth",
        "language": "英文",
        "publishYear": 2023,
        "programLanguage": "Swift",
        "formats": [
            {
                "fmt": "PDF",
                "title": "城通网盘",
                "link": "/e_books/3908/webstorage_links/19814/to_link"
            },
            {
                "fmt": "EPUB",
                "title": "城通网盘",
                "link": "/e_books/3908/webstorage_links/19813/to_link"
            }
        ]
    },
    {
        "id": 3881,
        "title": "Test iOS Apps with UI Automation",
        "img": "http://image.banshujiang.cn/3881.jpeg?timestamp=1714480672955",
        "author": "Jonathan Penn",
        "language": "英文",
        "publishYear": 2013,
        "programLanguage": "",
        "formats": [
            {
                "fmt": "PDF",
                "title": "城通网盘",
                "link": "/e_books/3881/webstorage_links/19702/to_link"
            },
            {
                "fmt": "EPUB",
                "title": "城通网盘",
                "link": "/e_books/3881/webstorage_links/19701/to_link"
            }
        ]
    },
    {
        "id": 3869,
        "title": "Releasing HTML5 Games for Windows 8",
        "img": "http://image.banshujiang.cn/3869.jpeg?timestamp=1714476497283",
        "author": "Jesse Freeman",
        "language": "英文",
        "publishYear": 2013,
        "programLanguage": "HTML5",
        "formats": [
            {
                "fmt": "PDF",
                "title": "城通网盘",
                "link": "/e_books/3869/webstorage_links/19654/to_link"
            },
            {
                "fmt": "EPUB",
                "title": "城通网盘",
                "link": "/e_books/3869/webstorage_links/19653/to_link"
            }
        ]
    },
    {
        "id": 3860,
        "title": "Programming iOS 7 4th Edition",
        "img": "http://image.banshujiang.cn/3860.jpeg?timestamp=1714475447463",
        "author": "Matt Neuburg",
        "language": "英文",
        "publishYear": 2013,
        "programLanguage": "Objective-C",
        "formats": [
            {
                "fmt": "PDF",
                "title": "城通网盘",
                "link": "/e_books/3860/webstorage_links/19618/to_link"
            },
            {
                "fmt": "EPUB",
                "title": "城通网盘",
                "link": "/e_books/3860/webstorage_links/19617/to_link"
            }
        ]
    },
    {
        "id": 3848,
        "title": "Mobile HTML5",
        "img": "http://image.banshujiang.cn/3848.jpeg?timestamp=1713969943714",
        "author": "Mobile HTML5",
        "language": "英文",
        "publishYear": 2013,
        "programLanguage": "HTML5",
        "formats": [
            {
                "fmt": "PDF",
                "title": "城通网盘",
                "link": "/e_books/3848/webstorage_links/19570/to_link"
            },
            {
                "fmt": "EPUB",
                "title": "城通网盘",
                "link": "/e_books/3848/webstorage_links/19569/to_link"
            }
        ]
    },
    {
        "id": 3843,
        "title": "iPad the missing manual 6th Edition",
        "img": "http://image.banshujiang.cn/3843.jpeg?timestamp=1713969065489",
        "author": "J.D. Biersdorfer",
        "language": "英文",
        "publishYear": 2013,
        "programLanguage": "",
        "formats": [
            {
                "fmt": "PDF",
                "title": "城通网盘",
                "link": "/e_books/3843/webstorage_links/19550/to_link"
            },
            {
                "fmt": "EPUB",
                "title": "城通网盘",
                "link": "/e_books/3843/webstorage_links/19549/to_link"
            }
        ]
    },
    {
        "id": 3841,
        "title": "HTML5 the missing manual 2nd Edition",
        "img": "http://image.banshujiang.cn/3841.jpeg?timestamp=1713968869460",
        "author": "Matthew MacDonald",
        "language": "英文",
        "publishYear": 2013,
        "programLanguage": "HTML5",
        "formats": [
            {
                "fmt": "PDF",
                "title": "城通网盘",
                "link": "/e_books/3841/webstorage_links/19542/to_link"
            },
            {
                "fmt": "EPUB",
                "title": "城通网盘",
                "link": "/e_books/3841/webstorage_links/19541/to_link"
            }
        ]
    },
    {
        "id": 3833,
        "title": "Developing Windows Store Apps with HTML5 and JavaScript",
        "img": "http://image.banshujiang.cn/3833.jpeg?timestamp=1713692825107",
        "author": "Rami Sarieddine",
        "language": "英文",
        "publishYear": 2013,
        "programLanguage": "HTML5",
        "formats": [
            {
                "fmt": "PDF",
                "title": "城通网盘",
                "link": "/e_books/3833/webstorage_links/19512/to_link"
            },
            {
                "fmt": "EPUB",
                "title": "城通网盘",
                "link": "/e_books/3833/webstorage_links/19511/to_link"
            }
        ]
    },
    {
        "id": 3815,
        "title": "iOS 7 Programming Fundamentals",
        "img": "http://image.banshujiang.cn/3815.jpeg?timestamp=1712977153520",
        "author": "Matt Neuburg",
        "language": "英文",
        "publishYear": 2013,
        "programLanguage": "Objective-C",
        "formats": [
            {
                "fmt": "PDF",
                "title": "城通网盘",
                "link": "/e_books/3815/webstorage_links/19440/to_link"
            },
            {
                "fmt": "EPUB",
                "title": "城通网盘",
                "link": "/e_books/3815/webstorage_links/19439/to_link"
            }
        ]
    },
    {
        "id": 3814,
        "title": "HTML5 and CSS3 2nd Edition",
        "img": "http://image.banshujiang.cn/3814.jpeg?timestamp=1712976771976",
        "author": "Brian P. Hogan",
        "language": "英文",
        "publishYear": 2013,
        "programLanguage": "HTML5",
        "formats": [
            {
                "fmt": "PDF",
                "title": "城通网盘",
                "link": "/e_books/3814/webstorage_links/19436/to_link"
            },
            {
                "fmt": "EPUB",
                "title": "城通网盘",
                "link": "/e_books/3814/webstorage_links/19435/to_link"
            }
        ]
    },
    {
        "id": 3795,
        "title": "Pro Objective-C",
        "img": "https://imagebsj.netlify.app/3795.jpeg",
        "author": "Keith Lee",
        "language": "英文",
        "publishYear": 2013,
        "programLanguage": "Objective-C",
        "formats": [
            {
                "fmt": "EPUB",
                "title": "城通网盘",
                "link": "/e_books/3795/webstorage_links/19362/to_link"
            },
            {
                "fmt": "PDF",
                "title": "百度网盘",
                "link": "/e_books/3795/webstorage_links/19361/to_link"
            }
        ]
    },
    {
        "id": 3764,
        "title": "Learn HTML5 by Creating Fun Games",
        "img": "https://imagebsj.netlify.app/3764.jpeg",
        "author": "Rodrigo Silveira",
        "language": "英文",
        "publishYear": 2013,
        "programLanguage": "HTML5",
        "formats": [
            {
                "fmt": "PDF",
                "title": "城通网盘",
                "link": "/e_books/3764/webstorage_links/19239/to_link"
            },
            {
                "fmt": "EPUB",
                "title": "城通网盘",
                "link": "/e_books/3764/webstorage_links/19238/to_link"
            }
        ]
    },
    {
        "id": 3761,
        "title": "iPhone The Missing Manual 7th Edition",
        "img": "https://imagebsj.netlify.app/3761.jpeg",
        "author": "David Pogue",
        "language": "英文",
        "publishYear": 2013,
        "programLanguage": "",
        "formats": [
            {
                "fmt": "PDF",
                "title": "城通网盘",
                "link": "/e_books/3761/webstorage_links/19227/to_link"
            },
            {
                "fmt": "EPUB",
                "title": "城通网盘",
                "link": "/e_books/3761/webstorage_links/19226/to_link"
            }
        ]
    },
    {
        "id": 3760,
        "title": "HTML5 Web Application Development By Example Beginner&#39;s guide",
        "img": "http://image.banshujiang.cn/3760.jpeg?timestamp=1712400094484",
        "author": "J.M. Gustafson",
        "language": "英文",
        "publishYear": 2013,
        "programLanguage": "HTML5",
        "formats": [
            {
                "fmt": "PDF",
                "title": "城通网盘",
                "link": "/e_books/3760/webstorage_links/19223/to_link"
            },
            {
                "fmt": "EPUB",
                "title": "城通网盘",
                "link": "/e_books/3760/webstorage_links/19222/to_link"
            }
        ]
    },
    {
        "id": 3759,
        "title": "Hello! IOS Development",
        "img": "http://image.banshujiang.cn/3759.jpeg?timestamp=1712399988596",
        "author": "Lou Franco and Eitan Mendelowitz",
        "language": "英文",
        "publishYear": 2013,
        "programLanguage": "Objective-C",
        "formats": [
            {
                "fmt": "PDF",
                "title": "城通网盘",
                "link": "/e_books/3759/webstorage_links/19219/to_link"
            },
            {
                "fmt": "EPUB",
                "title": "城通网盘",
                "link": "/e_books/3759/webstorage_links/19218/to_link"
            }
        ]
    }
]