[
    {
        "id": 809,
        "title": "Pro iOS Web Design and Development: HTML5, CSS3, and JavaScript with Safari",
        "img": "https://imagebsj.netlify.app/809.jpeg",
        "author": "Andrea Picchi",
        "language": "英文",
        "publishYear": 2011,
        "programLanguage": "HTML5",
        "formats": [
            {
                "fmt": "PDF",
                "title": "城通网盘",
                "link": "/e_books/809/webstorage_links/15132/to_link"
            }
        ]
    },
    {
        "id": 3730,
        "title": "HTML5: Pocket Reference 5th Edition",
        "img": "http://image.banshujiang.cn/3730.jpeg?timestamp=1711720283832",
        "author": "Jennifer Niederst Robbins",
        "language": "英文",
        "publishYear": 2013,
        "programLanguage": "HTML5",
        "formats": [
            {
                "fmt": "PDF",
                "title": "城通网盘",
                "link": "/e_books/3730/webstorage_links/19105/to_link"
            },
            {
                "fmt": "EPUB",
                "title": "城通网盘",
                "link": "/e_books/3730/webstorage_links/19104/to_link"
            }
        ]
    },
    {
        "id": 3661,
        "title": "HTML5 Canvas 2nd Edition",
        "img": "http://image.banshujiang.cn/3661.jpeg?timestamp=1709955832994",
        "author": "Steve Fulton and Jeff Fulton",
        "language": "英文",
        "publishYear": 2013,
        "programLanguage": "HTML5",
        "formats": [
            {
                "fmt": "PDF",
                "title": "城通网盘",
                "link": "/e_books/3661/webstorage_links/18839/to_link"
            },
            {
                "fmt": "EPUB",
                "title": "城通网盘",
                "link": "/e_books/3661/webstorage_links/18838/to_link"
            }
        ]
    },
    {
        "id": 3623,
        "title": "SwiftUI Animations by Tutorials",
        "img": "http://image.banshujiang.cn/3623.jpeg?timestamp=1708772434058",
        "author": "Irina Galata &amp; Bill Morefield",
        "language": "英文",
        "publishYear": 2022,
        "programLanguage": "Swift",
        "formats": [
            {
                "fmt": "PDF",
                "title": "城通网盘",
                "link": "/e_books/3623/webstorage_links/18703/to_link"
            },
            {
                "fmt": "EPUB",
                "title": "城通网盘",
                "link": "/e_books/3623/webstorage_links/18702/to_link"
            }
        ]
    },
    {
        "id": 3618,
        "title": "Push Notifications by Tutorials 4th Edition",
        "img": "http://image.banshujiang.cn/3618.jpeg?timestamp=1708054143788",
        "author": "Scott Grosch",
        "language": "英文",
        "publishYear": 2022,
        "programLanguage": "Swift",
        "formats": [
            {
                "fmt": "PDF",
                "title": "城通网盘",
                "link": "/e_books/3618/webstorage_links/18687/to_link"
            },
            {
                "fmt": "EPUB",
                "title": "城通网盘",
                "link": "/e_books/3618/webstorage_links/18686/to_link"
            }
        ]
    },
    {
        "id": 3559,
        "title": "Modern Concurrency in Swift 2nd Edition",
        "img": "http://image.banshujiang.cn/3559.jpeg?timestamp=1697274441182",
        "author": "Marin Todorov",
        "language": "英文",
        "publishYear": 2023,
        "programLanguage": "Swift",
        "formats": [
            {
                "fmt": "PDF",
                "title": "城通网盘",
                "link": "/e_books/3559/webstorage_links/18497/to_link"
            },
            {
                "fmt": "EPUB",
                "title": "城通网盘",
                "link": "/e_books/3559/webstorage_links/18496/to_link"
            }
        ]
    },
    {
        "id": 3541,
        "title": "Advanced Apple Debugging &amp; Reverse Engineering",
        "img": "http://image.banshujiang.cn/3541.jpeg?timestamp=1697273649437",
        "author": "Walter Tyree",
        "language": "英文",
        "publishYear": 2023,
        "programLanguage": "Python",
        "formats": [
            {
                "fmt": "PDF",
                "title": "城通网盘",
                "link": "/e_books/3541/webstorage_links/18434/to_link"
            },
            {
                "fmt": "EPUB",
                "title": "城通网盘",
                "link": "/e_books/3541/webstorage_links/18435/to_link"
            }
        ]
    },
    {
        "id": 3500,
        "title": "SwiftUI Essentials iOS 16 Edition",
        "img": "http://image.banshujiang.cn/3500.jpeg?timestamp=1696560670634",
        "author": "",
        "language": "英文",
        "publishYear": 2022,
        "programLanguage": "Swift",
        "formats": [
            {
                "fmt": "PDF",
                "title": "城通网盘",
                "link": "/e_books/3500/webstorage_links/18263/to_link"
            },
            {
                "fmt": "EPUB",
                "title": "城通网盘",
                "link": "/e_books/3500/webstorage_links/18262/to_link"
            }
        ]
    },
    {
        "id": 3482,
        "title": "iOS 16 App Development Essentials UIKit Edition",
        "img": "http://image.banshujiang.cn/3482.jpeg?timestamp=1696510994983",
        "author": "",
        "language": "英文",
        "publishYear": 2023,
        "programLanguage": "Swift",
        "formats": [
            {
                "fmt": "PDF",
                "title": "城通网盘",
                "link": "/e_books/3482/webstorage_links/18186/to_link"
            },
            {
                "fmt": "EPUB",
                "title": "城通网盘",
                "link": "/e_books/3482/webstorage_links/18187/to_link"
            }
        ]
    },
    {
        "id": 3476,
        "title": "Swift Apprentice",
        "img": "http://image.banshujiang.cn/3476.jpeg?timestamp=1696506533400",
        "author": "Janie Clayton",
        "language": "英文",
        "publishYear": 2016,
        "programLanguage": "Swift",
        "formats": [
            {
                "fmt": "PDF",
                "title": "城通网盘",
                "link": "/e_books/3476/webstorage_links/18159/to_link"
            }
        ]
    },
    {
        "id": 3463,
        "title": "Responsive Web Design with HTML5 and CSS3 2nd Edition",
        "img": "http://image.banshujiang.cn/3463.jpeg?timestamp=1696338349197",
        "author": "Ben Frain",
        "language": "英文",
        "publishYear": 2015,
        "programLanguage": "HTML5",
        "formats": [
            {
                "fmt": "PDF",
                "title": "城通网盘",
                "link": "/e_books/3463/webstorage_links/18089/to_link"
            },
            {
                "fmt": "EPUB",
                "title": "城通网盘",
                "link": "/e_books/3463/webstorage_links/18088/to_link"
            },
            {
                "fmt": "MOBI",
                "title": "城通网盘",
                "link": "/e_books/3463/webstorage_links/18091/to_link"
            },
            {
                "fmt": "CODE",
                "title": "城通网盘",
                "link": "/e_books/3463/webstorage_links/18090/to_link"
            }
        ]
    },
    {
        "id": 3438,
        "title": "iOS 10 Programming for Beginners",
        "img": "http://image.banshujiang.cn/3438.jpeg?timestamp=1686968768234",
        "author": "Craig Clayton",
        "language": "英文",
        "publishYear": 2016,
        "programLanguage": "Swift",
        "formats": [
            {
                "fmt": "PDF",
                "title": "城通网盘",
                "link": "/e_books/3438/webstorage_links/17947/to_link"
            },
            {
                "fmt": "EPUB",
                "title": "城通网盘",
                "link": "/e_books/3438/webstorage_links/17948/to_link"
            },
            {
                "fmt": "MOBI",
                "title": "城通网盘",
                "link": "/e_books/3438/webstorage_links/17949/to_link"
            }
        ]
    },
    {
        "id": 3424,
        "title": "Swift Development for the Apple Watch",
        "img": "http://image.banshujiang.cn/3424.jpeg?timestamp=1686457171825",
        "author": "Jon Manning and Paris Buttfield-Addison",
        "language": "英文",
        "publishYear": 2016,
        "programLanguage": "Swift",
        "formats": [
            {
                "fmt": "PDF",
                "title": "城通网盘",
                "link": "/e_books/3424/webstorage_links/17873/to_link"
            },
            {
                "fmt": "EPUB",
                "title": "城通网盘",
                "link": "/e_books/3424/webstorage_links/17872/to_link"
            }
        ]
    },
    {
        "id": 3416,
        "title": "Programming iOS 10 7th Edition",
        "img": "http://image.banshujiang.cn/3416.jpeg?timestamp=1681544166216",
        "author": "Matt Neuburg",
        "language": "英文",
        "publishYear": 2016,
        "programLanguage": "Swift",
        "formats": [
            {
                "fmt": "PDF",
                "title": "城通网盘",
                "link": "/e_books/3416/webstorage_links/17842/to_link"
            },
            {
                "fmt": "EPUB",
                "title": "城通网盘",
                "link": "/e_books/3416/webstorage_links/17843/to_link"
            }
        ]
    },
    {
        "id": 3405,
        "title": "Learning Swift 2nd Edition",
        "img": "http://image.banshujiang.cn/3405.jpeg?timestamp=1681021583194",
        "author": "Jon Manning, Paris Buttfield-Addison, and Tim Nugent",
        "language": "英文",
        "publishYear": 2017,
        "programLanguage": "Swift",
        "formats": [
            {
                "fmt": "PDF",
                "title": "城通网盘",
                "link": "/e_books/3405/webstorage_links/17796/to_link"
            },
            {
                "fmt": "EPUB",
                "title": "城通网盘",
                "link": "/e_books/3405/webstorage_links/17797/to_link"
            }
        ]
    },
    {
        "id": 3396,
        "title": "iPhone The Missing Manual 10th Edition",
        "img": "http://image.banshujiang.cn/3396.jpeg?timestamp=1677326194769",
        "author": "David Pogue",
        "language": "英文",
        "publishYear": 2017,
        "programLanguage": "",
        "formats": [
            {
                "fmt": "PDF",
                "title": "城通网盘",
                "link": "/e_books/3396/webstorage_links/17761/to_link"
            },
            {
                "fmt": "EPUB",
                "title": "城通网盘",
                "link": "/e_books/3396/webstorage_links/17763/to_link"
            },
            {
                "fmt": "MOBI",
                "title": "城通网盘",
                "link": "/e_books/3396/webstorage_links/17762/to_link"
            }
        ]
    }
]