{
    "id": 1939,
    "title": "Scala High Performance Programming",
    "img": "https://imagebsj.netlify.app/1939.jpeg",
    "author": "Vincent Theron and Michael Diamant",
    "language": "英文",
    "publishYear": 2016,
    "programLanguage": "",
    "formats": [
        {
            "fmt": "PDF",
            "title": "城通网盘",
            "link": "/e_books/1939/webstorage_links/11527/to_link"
        },
        {
            "fmt": "EPUB",
            "title": "城通网盘",
            "link": "/e_books/1939/webstorage_links/11526/to_link"
        },
        {
            "fmt": "MOBI",
            "title": "城通网盘",
            "link": "/e_books/1939/webstorage_links/11528/to_link"
        }
    ]
}