{
    "id": 3629,
    "title": "x64 Assembly Language Step- by- Step 4th Edition",
    "img": "http://image.banshujiang.cn/3629.jpeg?timestamp=1708773630471",
    "author": "Jeff Duntemann",
    "language": "英文",
    "publishYear": 2023,
    "programLanguage": "",
    "formats": [
        {
            "fmt": "PDF",
            "title": "城通网盘",
            "link": "/e_books/3629/webstorage_links/18725/to_link"
        },
        {
            "fmt": "EPUB",
            "title": "城通网盘",
            "link": "/e_books/3629/webstorage_links/18724/to_link"
        }
    ]
}