{
    "id": 3696,
    "title": "Web Audio API",
    "img": "http://image.banshujiang.cn/3696.jpeg?timestamp=1711704929043",
    "author": "Boris Smus",
    "language": "英文",
    "publishYear": 2013,
    "programLanguage": "",
    "formats": [
        {
            "fmt": "PDF",
            "title": "城通网盘",
            "link": "/e_books/3696/webstorage_links/18969/to_link"
        },
        {
            "fmt": "EPUB",
            "title": "城通网盘",
            "link": "/e_books/3696/webstorage_links/18968/to_link"
        }
    ]
}