{
    "id": 3731,
    "title": "iCloud for Developers",
    "img": "http://image.banshujiang.cn/3731.jpeg?timestamp=1711720409368",
    "author": "Cesare Rocchi",
    "language": "英文",
    "publishYear": 2013,
    "programLanguage": "",
    "formats": [
        {
            "fmt": "PDF",
            "title": "城通网盘",
            "link": "/e_books/3731/webstorage_links/19109/to_link"
        },
        {
            "fmt": "EPUB",
            "title": "城通网盘",
            "link": "/e_books/3731/webstorage_links/19108/to_link"
        }
    ]
}