{
    "id": 3896,
    "title": "Visual Studio 2012 and .NET 4.5 Expert Development Cookbook",
    "img": "http://image.banshujiang.cn/3896.jpeg?timestamp=1714483179836",
    "author": "Abhishek Sur",
    "language": "英文",
    "publishYear": 2013,
    "programLanguage": "C#",
    "formats": [
        {
            "fmt": "PDF",
            "title": "城通网盘",
            "link": "/e_books/3896/webstorage_links/19762/to_link"
        },
        {
            "fmt": "EPUB",
            "title": "城通网盘",
            "link": "/e_books/3896/webstorage_links/19761/to_link"
        }
    ]
}