{
    "id": 3900,
    "title": "Yii Application Development Cookbook 2nd Edition",
    "img": "http://image.banshujiang.cn/3900.jpeg?timestamp=1714483436819",
    "author": "Alexander Makarov",
    "language": "英文",
    "publishYear": 2013,
    "programLanguage": "",
    "formats": [
        {
            "fmt": "PDF",
            "title": "城通网盘",
            "link": "/e_books/3900/webstorage_links/19778/to_link"
        },
        {
            "fmt": "EPUB",
            "title": "城通网盘",
            "link": "/e_books/3900/webstorage_links/19777/to_link"
        }
    ]
}