{
    "id": 4066,
    "title": "Professional iOS Programming",
    "img": "http://image.banshujiang.cn/4066.jpeg?timestamp=1717199305174",
    "author": "Peter van de Put",
    "language": "英文",
    "publishYear": 2013,
    "programLanguage": "Objective-C",
    "formats": [
        {
            "fmt": "PDF",
            "title": "城通网盘",
            "link": "/e_books/4066/webstorage_links/20406/to_link"
        },
        {
            "fmt": "EPUB",
            "title": "城通网盘",
            "link": "/e_books/4066/webstorage_links/20405/to_link"
        }
    ]
}