{
    "id": 4085,
    "title": "Generative AI Art",
    "img": "http://image.banshujiang.cn/4085.jpeg?timestamp=1717323375502",
    "author": "Oliver Theobald",
    "language": "英文",
    "publishYear": 2022,
    "programLanguage": "",
    "formats": [
        {
            "fmt": "PDF",
            "title": "城通网盘",
            "link": "/e_books/4085/webstorage_links/20479/to_link"
        },
        {
            "fmt": "EPUB",
            "title": "城通网盘",
            "link": "/e_books/4085/webstorage_links/20478/to_link"
        }
    ]
}