{
    "id": 4234,
    "title": "Node Security",
    "img": "http://image.banshujiang.cn/4234.jpeg?timestamp=1719051490952",
    "author": "Dominic Barnes",
    "language": "英文",
    "publishYear": 2013,
    "programLanguage": "",
    "formats": [
        {
            "fmt": "PDF",
            "title": "城通网盘",
            "link": "/e_books/4234/webstorage_links/21127/to_link"
        },
        {
            "fmt": "EPUB",
            "title": "城通网盘",
            "link": "/e_books/4234/webstorage_links/21126/to_link"
        }
    ]
}