{
    "id": 4440,
    "title": "Kubernetes进阶实战",
    "img": "http://image.banshujiang.cn/4440.jpeg?timestamp=1723345301857",
    "author": "马永亮",
    "language": "中文",
    "publishYear": 2019,
    "programLanguage": "",
    "formats": [
        {
            "fmt": "EPUB",
            "title": "城通网盘",
            "link": "/e_books/4440/webstorage_links/21890/to_link"
        },
        {
            "fmt": "MOBI",
            "title": "城通网盘",
            "link": "/e_books/4440/webstorage_links/21891/to_link"
        },
        {
            "fmt": "AZW3",
            "title": "城通网盘",
            "link": "/e_books/4440/webstorage_links/21889/to_link"
        }
    ]
}