{
    "id": 4772,
    "title": "Learning JavaScript 3rd Edition",
    "img": "http://image.banshujiang.cn/4772.jpeg?timestamp=1730535181646",
    "author": "Ethan Brown",
    "language": "英文",
    "publishYear": 2016,
    "programLanguage": "JavaScript",
    "formats": [
        {
            "fmt": "PDF",
            "title": "城通网盘",
            "link": "/e_books/4772/webstorage_links/23284/to_link"
        },
        {
            "fmt": "EPUB",
            "title": "城通网盘",
            "link": "/e_books/4772/webstorage_links/23282/to_link"
        },
        {
            "fmt": "MOBI",
            "title": "城通网盘",
            "link": "/e_books/4772/webstorage_links/23283/to_link"
        }
    ]
}