{
    "id": 4823,
    "title": "Decentralized Applications",
    "img": "http://image.banshujiang.cn/4823.jpeg?timestamp=1731737197311",
    "author": "Siraj Raval",
    "language": "英文",
    "publishYear": 2016,
    "programLanguage": "",
    "formats": [
        {
            "fmt": "PDF",
            "title": "城通网盘",
            "link": "/e_books/4823/webstorage_links/23478/to_link"
        },
        {
            "fmt": "EPUB",
            "title": "城通网盘",
            "link": "/e_books/4823/webstorage_links/23476/to_link"
        },
        {
            "fmt": "MOBI",
            "title": "城通网盘",
            "link": "/e_books/4823/webstorage_links/23477/to_link"
        }
    ]
}