{
    "id": 4906,
    "title": "Implementing Data Mesh",
    "img": "http://image.banshujiang.cn/4906.jpeg?timestamp=1739087497809",
    "author": "Jean-Georges Perrin and Eric Broda",
    "language": "英文",
    "publishYear": 2024,
    "programLanguage": "",
    "formats": [
        {
            "fmt": "PDF",
            "title": "城通网盘",
            "link": "/e_books/4906/webstorage_links/23826/to_link"
        },
        {
            "fmt": "EPUB",
            "title": "城通网盘",
            "link": "/e_books/4906/webstorage_links/23825/to_link"
        }
    ]
}