{
    "id": 5210,
    "title": "Python自动化运维：技术与最佳实践",
    "img": "http://image.banshujiang.cn/5210.jpeg?timestamp=1754139928763",
    "author": "刘天斯",
    "language": "中文",
    "publishYear": 2014,
    "programLanguage": "Python",
    "formats": [
        {
            "fmt": "EPUB",
            "title": "城通网盘",
            "link": "/e_books/5210/webstorage_links/24666/to_link"
        },
        {
            "fmt": "MOBI",
            "title": "城通网盘",
            "link": "/e_books/5210/webstorage_links/24667/to_link"
        },
        {
            "fmt": "AZW3",
            "title": "城通网盘",
            "link": "/e_books/5210/webstorage_links/24665/to_link"
        }
    ]
}